esgprofiler/__init__.py
esgprofiler/config.py
esgprofiler/dashboard.py
esgprofiler/data_ingest.py
esgprofiler/nlp_extract.py
esgprofiler/scoring.py
esgprofiler/utils.py
esgprofiler-0.1.3.dist-info/METADATA
esgprofiler-0.1.3.dist-info/WHEEL
esgprofiler-0.1.3.dist-info/entry_points.txt
esgprofiler-0.1.3.dist-info/top_level.txt
esgprofiler-0.1.3.dist-info/RECORD
