Metadata-Version: 2.4
Name: esgprofiler
Version: 0.1.3
Summary: Automated ESG scoring and profiling for companies using NLP and open data sources.
Home-page: https://github.com/advait27/ESGProfiler.git
Author: Advait Dharmadhikari
Author-email: advaituni@gmail.com
License: MIT
Project-URL: Documentation, https://github.com/advait27/ESGProfiler.git
Project-URL: Source, https://github.com/advait27/ESGProfiler.git
Project-URL: Bug Tracker, https://github.com/advait27/ESGProfiler.git/issues
Classifier: Programming Language :: Python :: 3
Classifier: Intended Audience :: Developers
Classifier: Intended Audience :: Financial and Insurance Industry
Classifier: License :: OSI Approved :: MIT License
Classifier: Operating System :: OS Independent
Classifier: Topic :: Software Development :: Libraries :: Python Modules
Classifier: Topic :: Office/Business :: Financial
Classifier: Natural Language :: English
Classifier: Development Status :: 3 - Alpha
Requires-Python: >=3.11
Requires-Dist: streamlit
Requires-Dist: pandas
Requires-Dist: numpy
Requires-Dist: requests
Requires-Dist: beautifulsoup4
Requires-Dist: yfinance
Requires-Dist: scikit-learn
Requires-Dist: spacy
Requires-Dist: transformers
Requires-Dist: sec-edgar-downloader
Requires-Dist: plotly
Dynamic: author
Dynamic: author-email
Dynamic: classifier
Dynamic: description
Dynamic: description-content-type
Dynamic: home-page
Dynamic: license
Dynamic: project-url
Dynamic: requires-dist
Dynamic: requires-python
Dynamic: summary
